setup.py
django_image_dimensions.egg-info/PKG-INFO
django_image_dimensions.egg-info/SOURCES.txt
django_image_dimensions.egg-info/dependency_links.txt
django_image_dimensions.egg-info/requires.txt
django_image_dimensions.egg-info/top_level.txt
imagedimensions/__init__.py
imagedimensions/middleware.py
imagedimensions/models.py
imagedimensions/tasks.py
imagedimensions/tests.py
imagedimensions/views.py
imagedimensions/templatetags/__init__.py
imagedimensions/templatetags/imgdimensions.py