Metadata-Version: 1.0
Name: django-image-dimensions
Version: 0.0.4
Summary: Automatically add dimension attributes to all <img> tags in a response to improve rendering speed on the client. 
Home-page: https://github.com/InviteBox/django-image-dimensions
Author: Alexander Tereshkin
Author-email: atereshkin@invitebox.com
License: BSD
Keywords: django images performance
Platform: UNKNOWN
Classifier: Development Status :: 3 - Alpha
Classifier: Topic :: Software Development
Classifier: Framework :: Django
Classifier: Intended Audience :: Developers
Classifier: License :: OSI Approved :: BSD License
